geococo/__init__.py
geococo/cli.py
geococo/coco_manager.py
geococo/coco_models.py
geococo/coco_processing.py
geococo/utils.py
geococo/window_schema.py
geococo-0.7.0.dist-info/METADATA
geococo-0.7.0.dist-info/WHEEL
geococo-0.7.0.dist-info/entry_points.txt
geococo-0.7.0.dist-info/licenses/LICENSE
geococo-0.7.0.dist-info/RECORD
