Metadata-Version: 2.4
Name: geococo
Version: 0.7.0
Summary: Converts GIS annotations to Microsoft's Common Objects In Context (COCO) dataset format
Author-email: Jasper Siebring <j.siebring92@gmail.com>
License-File: LICENSE
Keywords: ai,annotation,arcgis,coco,deep-learning,gis,labeling,qgis,yolo
Requires-Python: >=3.9
Requires-Dist: geopandas>=0.13.2
Requires-Dist: opencv-python-headless>=4.8.0.76
Requires-Dist: pandera[geopandas]>=0.16.1
Requires-Dist: pycocotools>=2.0.7
Requires-Dist: pydantic<2.0,>=1.10.13
Requires-Dist: rasterio>=1.3.8
Requires-Dist: semver>=3.0.1
Requires-Dist: tqdm>=4.66.3
Requires-Dist: typer>=0.9.0
Requires-Dist: typing-extensions>=4.7.1
Provides-Extra: fiftyone
Requires-Dist: fiftyone>=1.5.2; extra == 'fiftyone'
